eva/__init__.py
eva/__main__.py
eva/__version__.py
eva/core/__init__.py
eva/core/callbacks/__init__.py
eva/core/callbacks/config.py
eva/core/callbacks/writers/__init__.py
eva/core/callbacks/writers/embeddings/__init__.py
eva/core/callbacks/writers/embeddings/_manifest.py
eva/core/callbacks/writers/embeddings/base.py
eva/core/callbacks/writers/embeddings/classification.py
eva/core/callbacks/writers/embeddings/segmentation.py
eva/core/callbacks/writers/embeddings/typings.py
eva/core/cli/__init__.py
eva/core/cli/cli.py
eva/core/cli/logo.py
eva/core/cli/setup.py
eva/core/data/__init__.py
eva/core/data/dataloaders/__init__.py
eva/core/data/dataloaders/dataloader.py
eva/core/data/datamodules/__init__.py
eva/core/data/datamodules/call.py
eva/core/data/datamodules/datamodule.py
eva/core/data/datamodules/schemas.py
eva/core/data/datasets/__init__.py
eva/core/data/datasets/base.py
eva/core/data/datasets/classification/__init__.py
eva/core/data/datasets/classification/embeddings.py
eva/core/data/datasets/classification/multi_embeddings.py
eva/core/data/datasets/dataset.py
eva/core/data/datasets/embeddings.py
eva/core/data/datasets/typings.py
eva/core/data/samplers/__init__.py
eva/core/data/samplers/classification/__init__.py
eva/core/data/samplers/classification/balanced.py
eva/core/data/samplers/classification/base.py
eva/core/data/samplers/classification/stratified_random.py
eva/core/data/samplers/random.py
eva/core/data/samplers/sampler.py
eva/core/data/splitting/__init__.py
eva/core/data/splitting/random.py
eva/core/data/splitting/stratified.py
eva/core/data/transforms/__init__.py
eva/core/data/transforms/dtype/__init__.py
eva/core/data/transforms/dtype/array.py
eva/core/data/transforms/padding/__init__.py
eva/core/data/transforms/padding/pad_2d_tensor.py
eva/core/data/transforms/sampling/__init__.py
eva/core/data/transforms/sampling/sample_from_axis.py
eva/core/interface/__init__.py
eva/core/interface/interface.py
eva/core/loggers/__init__.py
eva/core/loggers/dummy.py
kaiko_eva-0.4.3.dist-info/METADATA
kaiko_eva-0.4.3.dist-info/WHEEL
kaiko_eva-0.4.3.dist-info/entry_points.txt
kaiko_eva-0.4.3.dist-info/licenses/LICENSE
kaiko_eva-0.4.3.dist-info/RECORD
