Metadata-Version: 2.1
Name: kaiko-eva
Version: 0.4.3
Summary: Evaluation Framework for oncology foundation models.
Keywords: machine-learning,evaluation-framework,oncology,foundation-models
Author-Email: Ioannis Gatopoulos <ioannis@kaiko.ai>, =?utf-8?q?Nicolas_K=C3=A4nzig?= <nicolas@kaiko.ai>, Roman Moser <roman@kaiko.ai>
Maintainer-Email: Ioannis Gatopoulos <ioannis@kaiko.ai>, =?utf-8?q?Nicolas_K=C3=A4nzig?= <nicolas@kaiko.ai>, Roman Moser <roman@kaiko.ai>
License:                                  Apache License
Classifier: Topic :: Software Development :: Build Tools
Classifier: Programming Language :: Python :: 3
Classifier: Programming Language :: Python :: 3.10
Classifier: Programming Language :: Python :: 3.11
Classifier: Programming Language :: Python :: 3.12
Project-URL: Homepage, https://kaiko-ai.github.io/eva/dev/
Project-URL: Repository, https://github.com/kaiko-ai/eva
Project-URL: Documentation, https://kaiko-ai.github.io/eva/dev/
Requires-Python: >=3.10
Requires-Dist: torch>=2.3.0
Requires-Dist: lightning>=2.2.0
Requires-Dist: jsonargparse[omegaconf]>=4.30.0
Requires-Dist: tensorboard>=2.16.2
Requires-Dist: loguru>=0.7.2
Requires-Dist: pandas>=2.0.0
Requires-Dist: transformers>=4.38.2
Requires-Dist: onnxruntime>=1.15.1
Requires-Dist: onnx>=1.16.0
Requires-Dist: toolz>=0.12.1
Requires-Dist: rich>=13.7.1
Requires-Dist: torchmetrics>=1.6.0
Requires-Dist: nibabel>=3.2.2
Provides-Extra: vision
Requires-Dist: h5py>=3.10.0; extra == "vision"
Requires-Dist: nibabel>=4.0.1; extra == "vision"
Requires-Dist: opencv-python-headless>=4.9.0.80; extra == "vision"
Requires-Dist: timm>=1.0.9; extra == "vision"
Requires-Dist: torchvision>=0.17.0; extra == "vision"
Requires-Dist: openslide-python>=1.3.1; extra == "vision"
Requires-Dist: gdown>=5.2.0; extra == "vision"
Requires-Dist: scikit-image>=0.24.0; extra == "vision"
Requires-Dist: imagesize>=1.4.1; extra == "vision"
Requires-Dist: scipy>=1.14.0; extra == "vision"
Requires-Dist: monai>=1.3.2; extra == "vision"
Requires-Dist: einops>=0.8.1; extra == "vision"
Provides-Extra: language
Requires-Dist: datasets<4.0.0,>=2.19.0; extra == "language"
Requires-Dist: litellm>=1.61.8; extra == "language"
Requires-Dist: backoff>=2.2.1; extra == "language"
Requires-Dist: json-repair>=0.52.0; extra == "language"
Provides-Extra: multimodal
Requires-Dist: litellm>=1.61.8; extra == "multimodal"
Requires-Dist: backoff>=2.2.1; extra == "multimodal"
Requires-Dist: json-repair>=0.52.0; extra == "multimodal"
Provides-Extra: all
Requires-Dist: h5py>=3.10.0; extra == "all"
Requires-Dist: nibabel>=4.0.1; extra == "all"
Requires-Dist: opencv-python-headless>=4.9.0.80; extra == "all"
Requires-Dist: timm>=1.0.9; extra == "all"
Requires-Dist: torchvision>=0.17.0; extra == "all"
Requires-Dist: openslide-python>=1.3.1; extra == "all"
Requires-Dist: gdown>=5.2.0; extra == "all"
Requires-Dist: scikit-image>=0.24.0; extra == "all"
Requires-Dist: imagesize>=1.4.1; extra == "all"
Requires-Dist: scipy>=1.14.0; extra == "all"
Requires-Dist: monai>=1.3.2; extra == "all"
Requires-Dist: einops>=0.8.1; extra == "all"
Requires-Dist: datasets<4.0.0,>=2.19.0; extra == "all"
Requires-Dist: litellm>=1.61.8; extra == "all"
Requires-Dist: backoff>=2.2.1; extra == "all"
Requires-Dist: json-repair>=0.52.0; extra == "all"
